.hgignore
LICENCE.txt
README.rst
setup.py
django_signature.egg-info/PKG-INFO
django_signature.egg-info/SOURCES.txt
django_signature.egg-info/dependency_links.txt
django_signature.egg-info/top_level.txt
signature/__init__.py
signature/admin.py
signature/models.py
signature/openssl.cnf
signature/openssl.py
signature/settings.py
signature/utils.py
tests/bootstrap.py
tests/buildout.cfg
tests/test_project/__init__.py
tests/test_project/settings.py
tests/test_project/urls.py
tests/test_project/apps/__init__.py
tests/test_project/apps/testapp/__init__.py
tests/test_project/apps/testapp/models.py
tests/test_project/apps/testapp/tests.py
tests/test_project/apps/testapp/urls.py
tests/test_project/apps/testapp/certificates/__init__.py
tests/test_project/apps/testapp/certificates/client.crt
tests/test_project/apps/testapp/certificates/client.key
tests/test_project/apps/testapp/certificates/client.pub
tests/test_project/apps/testapp/certificates/client_req.pem
tests/test_project/apps/testapp/certificates/rootca.crt
tests/test_project/apps/testapp/certificates/rootca.key
tests/test_project/apps/testapp/certificates/user.crt
tests/test_project/apps/testapp/certificates/user.key
tests/test_project/apps/testapp/certificates/user_req.pem
tests/test_project/apps/testapp/certificates/utf8.pem
tests/test_project/media/afile.txt
tests/test_project/media/otherfile.txt
tests/test_project/media/wrongfile.txt
tests/test_project/templates/404.html
tests/test_project/templates/500.html