Metadata-Version: 1.1
Name: django-signature
Version: 0.3
Summary: Django application to generate and sign Models.
Home-page: http://github.com/bearstech/django-signature
Author: Johan Charpentier
Author-email: jcharpentier@bearstech.com
License: GPL v3
Download-URL: http://bitbucket.org/bearstech/django-signature/downloads
Keywords: django models crypto openssl pki
Platform: UNKNOWN
Classifier: Development Status :: 4 - Beta
Classifier: Environment :: Web Environment
Classifier: Framework :: Django
Classifier: Intended Audience :: Developers
Classifier: Programming Language :: Python
Classifier: Topic :: Software Development :: Libraries :: Python Modules
Requires: python (>= 2.4)
Requires: django (>= 1.1)
Requires: M2Crypto (>= 0.18)
